tutorial_packaging_python_projects/__init__.py
tutorial_packaging_python_projects/example.py
tutorial_packaging_python_projects-2024.8.4.dist-info/LICENSE
tutorial_packaging_python_projects-2024.8.4.dist-info/METADATA
tutorial_packaging_python_projects-2024.8.4.dist-info/WHEEL
tutorial_packaging_python_projects-2024.8.4.dist-info/top_level.txt
tutorial_packaging_python_projects-2024.8.4.dist-info/RECORD
