Metadata-Version: 2.1
Name: tutorial-packaging-python-projects
Version: 2024.8.4
Summary: Tutorial: Packaging Python Projects
Author-email: Christian Hänig <christian.haenig@hs-anhalt.de>
Project-URL: Gitlab, https://gitlab.hs-anhalt.de/ki/tutorial-packaging-python-projects
Project-URL: PyPI, https://pypi.org/project/tutorial-packaging-python-projects/
Classifier: Programming Language :: Python :: 3
Classifier: License :: OSI Approved :: MIT License
Classifier: Operating System :: OS Independent
Requires-Python: >=3.8
License-File: LICENSE
